{
    "_links": {
        "self": {
            "href": "http:\/\/default\/sites\/default\/files\/2019-05\/generateImage_ZR9an4.jpeg"
        },
        "type": {
            "href": "http:\/\/drupal.org\/rest\/type\/file\/file"
        },
        "http:\/\/drupal.org\/rest\/relation\/file\/file\/uid": [
            {
                "href": "http:\/\/default\/user\/1?_format=hal_json"
            }
        ]
    },
    "fid": [
        {
            "value": 11
        }
    ],
    "uuid": [
        {
            "value": "cd9fd4d0-d298-4338-aba2-092197986ec6"
        }
    ],
    "langcode": [
        {
            "value": "en"
        }
    ],
    "_embedded": {
        "http:\/\/drupal.org\/rest\/relation\/file\/file\/uid": [
            {
                "_links": {
                    "self": {
                        "href": "http:\/\/default\/user\/1?_format=hal_json"
                    },
                    "type": {
                        "href": "http:\/\/drupal.org\/rest\/type\/user\/user"
                    }
                },
                "uuid": [
                    {
                        "value": "e6190487-2c15-4bd5-a219-7f0f88479afb"
                    }
                ]
            }
        ]
    },
    "filename": [
        {
            "value": "generateImage_ZR9an4.jpeg"
        }
    ],
    "uri": [
        {
            "value": "public:\/\/2019-05\/generateImage_ZR9an4.jpeg",
            "url": "\/sites\/default\/files\/2019-05\/generateImage_ZR9an4.jpeg"
        }
    ],
    "filemime": [
        {
            "value": "image\/jpeg"
        }
    ],
    "filesize": [
        {
            "value": 8146
        }
    ],
    "status": [
        {
            "value": false
        }
    ],
    "created": [
        {
            "value": "2019-05-24T14:28:35+00:00",
            "format": "Y-m-d\\TH:i:sP"
        }
    ],
    "changed": [
        {
            "value": "2019-05-24T14:28:35+00:00",
            "format": "Y-m-d\\TH:i:sP"
        }
    ]
}